rtl/modules/alu.v
// ============================================================================
// ALU for RISC-V RV32I + M Extension (MUL, DIV)
// ============================================================================

module alu (
    input  wire [31:0] a,
    input  wire [31:0] b,
    input  wire [4:0]  op,
    output reg  [31:0] result,
    output wire        zero,
    output wire        carry_out,
    output wire        overflow
);

    // ========================================================================
    // ALU Operations
    // ========================================================================
    localparam OP_ADD    = 5'h00,
               OP_SUB    = 5'h01,
               OP_AND    = 5'h02,
               OP_OR     = 5'h03,
               OP_XOR    = 5'h04,
               OP_SLL    = 5'h05,
               OP_SRL    = 5'h06,
               OP_SRA    = 5'h07,
               OP_SLT    = 5'h08,
               OP_SLTU   = 5'h09,
               OP_MUL    = 5'h0A,
               OP_MULH   = 5'h0B,
               OP_MULHU  = 5'h0C,
               OP_MULHSU = 5'h0D,
               OP_DIV    = 5'h0E,
               OP_DIVU   = 5'h0F,
               OP_REM    = 5'h10,
               OP_REMU   = 5'h11,
               OP_COPY_A = 5'h12,
               OP_COPY_B = 5'h13;
    
    // ========================================================================
    // Internal Signals
    // ========================================================================
    reg [32:0] extended_result;
    reg [31:0] b_shift;
    reg [63:0] mult_result;
    reg [31:0] quotient, remainder;
    
    // ========================================================================
    // ALU Logic
    // ========================================================================
    always @(*) begin
        result = 32'h0;
        mult_result = 64'h0;
        quotient = 32'h0;
        remainder = 32'h0;
        
        case (op)
            // Arithmetic
            OP_ADD: begin
                extended_result = {1'b0, a} + {1'b0, b};
                result = extended_result[31:0];
            end
            
            OP_SUB: begin
                extended_result = {1'b0, a} - {1'b0, b};
                result = extended_result[31:0];
            end
            
            // Logical
            OP_AND: result = a & b;
            OP_OR:  result = a | b;
            OP_XOR: result = a ^ b;
            
            // Shifts
            OP_SLL: begin
                b_shift = b[4:0];
                result = a << b_shift;
            end
            
            OP_SRL: begin
                b_shift = b[4:0];
                result = a >> b_shift;
            end
            
            OP_SRA: begin
                b_shift = b[4:0];
                result = $signed(a) >>> b_shift;
            end
            
            // Compare
            OP_SLT: begin
                result = ($signed(a) < $signed(b)) ? 32'h1 : 32'h0;
            end
            
            OP_SLTU: begin
                result = (a < b) ? 32'h1 : 32'h0;
            end
            
            // ================================================================
            // M Extension - Multiplication
            // ================================================================
            OP_MUL: begin
                mult_result = $signed(a) * $signed(b);
                result = mult_result[31:0];
            end
            
            OP_MULH: begin
                mult_result = $signed(a) * $signed(b);
                result = mult_result[63:32];
            end
            
            OP_MULHU: begin
                mult_result = a * b;
                result = mult_result[63:32];
            end
            
            OP_MULHSU: begin
                mult_result = $signed(a) * b;
                result = mult_result[63:32];
            end
            
            // ================================================================
            // M Extension - Division
            // ================================================================
            OP_DIV: begin
                if (b != 32'h0) begin
                    quotient = $signed(a) / $signed(b);
                    result = quotient;
                end else begin
                    result = 32'hFFFFFFFF;
                end
            end
            
            OP_DIVU: begin
                if (b != 32'h0) begin
                    quotient = a / b;
                    result = quotient;
                end else begin
                    result = 32'hFFFFFFFF;
                end
            end
            
            OP_REM: begin
                if (b != 32'h0) begin
                    remainder = $signed(a) % $signed(b);
                    result = remainder;
                end else begin
                    result = a;
                end
            end
            
            OP_REMU: begin
                if (b != 32'h0) begin
                    remainder = a % b;
                    result = remainder;
                end else begin
                    result = a;
                end
            end
            
            // Copy
            OP_COPY_A: result = a;
            OP_COPY_B: result = b;
            
            default: result = 32'h0;
        endcase
    end
    
    // ========================================================================
    // Status Flags
    // ========================================================================
    assign zero = (result == 32'h0);
    assign carry_out = extended_result[32];
    assign overflow = ((op == OP_ADD) && (a[31] == b[31]) && (result[31] != a[31])) ||
                      ((op == OP_SUB) && (a[31] != b[31]) && (result[31] != a[31]));

endmodule

rtl/modules/control_unit.v
// ============================================================================
// Control Unit for RISC-V RV32I + M Extension
// ============================================================================

module control_unit (
    input  wire [6:0]  opcode,
    input  wire [2:0]  funct3,
    input  wire [6:0]  funct7,
    output reg         reg_write,
    output reg         mem_read,
    output reg         mem_write,
    output reg  [4:0]  alu_op,
    output reg  [1:0]  alu_src_a,
    output reg  [1:0]  alu_src_b,
    output reg  [2:0]  imm_type,
    output reg         branch,
    output reg         jump,
    output reg         jump_reg,
    output reg  [2:0]  branch_op
);

    // ========================================================================
    // ALU Operations (5-bit for M extension)
    // ========================================================================
    localparam ALU_ADD   = 5'h00,
               ALU_SUB   = 5'h01,
               ALU_AND   = 5'h02,
               ALU_OR    = 5'h03,
               ALU_XOR   = 5'h04,
               ALU_SLL   = 5'h05,
               ALU_SRL   = 5'h06,
               ALU_SRA   = 5'h07,
               ALU_SLT   = 5'h08,
               ALU_SLTU  = 5'h09,
               ALU_MUL   = 5'h0A,
               ALU_MULH  = 5'h0B,
               ALU_MULHU = 5'h0C,
               ALU_MULHSU= 5'h0D,
               ALU_DIV   = 5'h0E,
               ALU_DIVU  = 5'h0F,
               ALU_REM   = 5'h10,
               ALU_REMU  = 5'h11;
    
    // ========================================================================
    // Immediate Types
    // ========================================================================
    localparam IMM_I = 3'b000,
               IMM_S = 3'b001,
               IMM_B = 3'b010,
               IMM_U = 3'b011,
               IMM_J = 3'b100;
    
    // ========================================================================
    // Control Logic
    // ========================================================================
    always @(*) begin
        // Default values
        reg_write  = 1'b0;
        mem_read   = 1'b0;
        mem_write  = 1'b0;
        alu_op     = ALU_ADD;
        alu_src_a  = 2'b00;
        alu_src_b  = 2'b00;
        imm_type   = IMM_I;
        branch     = 1'b0;
        jump       = 1'b0;
        jump_reg   = 1'b0;
        branch_op  = 3'b000;
        
        case (opcode)
            7'b0110111: begin // LUI
                reg_write  = 1'b1;
                imm_type   = IMM_U;
                alu_src_a  = 2'b10;
                alu_src_b  = 2'b00;
                alu_op     = ALU_ADD;
            end
            
            7'b0010111: begin // AUIPC
                reg_write  = 1'b1;
                imm_type   = IMM_U;
                alu_src_a  = 2'b01;
                alu_src_b  = 2'b01;
                alu_op     = ALU_ADD;
            end
            
            7'b1101111: begin // JAL
                reg_write  = 1'b1;
                jump       = 1'b1;
                imm_type   = IMM_J;
                alu_src_a  = 2'b01;
                alu_src_b  = 2'b01;
                alu_op     = ALU_ADD;
            end
            
            7'b1100111: begin // JALR
                reg_write  = 1'b1;
                jump       = 1'b1;
                jump_reg   = 1'b1;
                imm_type   = IMM_I;
                alu_src_a  = 2'b01;
                alu_src_b  = 2'b01;
                alu_op     = ALU_ADD;
            end
            
            7'b1100011: begin // BRANCH
                branch     = 1'b1;
                branch_op  = funct3;
                imm_type   = IMM_B;
                alu_src_a  = 2'b00;
                alu_src_b  = 2'b00;
                alu_op     = ALU_SUB;
            end
            
            7'b0000011: begin // LOAD
                reg_write  = 1'b1;
                mem_read   = 1'b1;
                imm_type   = IMM_I;
                alu_src_a  = 2'b00;
                alu_src_b  = 2'b01;
                alu_op     = ALU_ADD;
            end
            
            7'b0100011: begin // STORE
                mem_write  = 1'b1;
                imm_type   = IMM_S;
                alu_src_a  = 2'b00;
                alu_src_b  = 2'b01;
                alu_op     = ALU_ADD;
            end
            
            7'b0010011: begin // OP-IMM
                reg_write  = 1'b1;
                imm_type   = IMM_I;
                alu_src_a  = 2'b00;
                alu_src_b  = 2'b01;
                case (funct3)
                    3'b000: alu_op = ALU_ADD;
                    3'b001: alu_op = ALU_SLL;
                    3'b010: alu_op = ALU_SLT;
                    3'b011: alu_op = ALU_SLTU;
                    3'b100: alu_op = ALU_XOR;
                    3'b101: alu_op = (funct7[5]) ? ALU_SRA : ALU_SRL;
                    3'b110: alu_op = ALU_OR;
                    3'b111: alu_op = ALU_AND;
                endcase
            end
            
            7'b0110011: begin // OP - Supports M Extension
                reg_write  = 1'b1;
                alu_src_a  = 2'b00;
                alu_src_b  = 2'b00;
                
                // ============================================================
                // M Extension Detection: funct7 == 0000001
                // ============================================================
                if (funct7 == 7'b0000001) begin
                    case (funct3)
                        3'b000: alu_op = ALU_MUL;    // MUL
                        3'b001: alu_op = ALU_MULH;   // MULH
                        3'b010: alu_op = ALU_MULHSU; // MULHSU
                        3'b011: alu_op = ALU_MULHU;  // MULHU
                        3'b100: alu_op = ALU_DIV;    // DIV
                        3'b101: alu_op = ALU_DIVU;   // DIVU
                        3'b110: alu_op = ALU_REM;    // REM
                        3'b111: alu_op = ALU_REMU;   // REMU
                        default: alu_op = ALU_ADD;
                    endcase
                end else begin
                    // ========================================================
                    // RV32I Base Instructions
                    // ========================================================
                    case (funct3)
                        3'b000: alu_op = (funct7[5]) ? ALU_SUB : ALU_ADD;
                        3'b001: alu_op = ALU_SLL;
                        3'b010: alu_op = ALU_SLT;
                        3'b011: alu_op = ALU_SLTU;
                        3'b100: alu_op = ALU_XOR;
                        3'b101: alu_op = (funct7[5]) ? ALU_SRA : ALU_SRL;
                        3'b110: alu_op = ALU_OR;
                        3'b111: alu_op = ALU_AND;
                        default: alu_op = ALU_ADD;
                    endcase
                end
            end
            
            7'b1110011: begin // SYSTEM
                // ecall, ebreak - no operation
            end
        endcase
    end

endmodule

rtl/core/riscv_core.v
module riscv_core (
    input  wire        clk,
    input  wire        rst_n,
    input  wire [31:0] instr_i,
    input  wire [31:0] data_i,
    output wire [31:0] pc_o,
    output wire [31:0] addr_o,
    output wire [31:0] data_o,
    output wire        mem_write_o,
    output wire        mem_read_o,
    output wire        halt_o
);

    reg [31:0] pc;
    wire [31:0] pc_plus_4;
    
    reg [31:0] reg_file [0:31];
    wire [31:0] rs1_data, rs2_data;
    
    wire [6:0] opcode;
    wire [2:0] funct3;
    wire [6:0] funct7;
    wire [4:0] rs1, rs2, rd;
    wire [31:0] imm;
    wire [2:0] imm_type;
    
    wire reg_write, mem_read, mem_write;
    wire [4:0] alu_op;
    wire [1:0] alu_src_a, alu_src_b;
    wire branch, jump, jump_reg;
    wire [2:0] branch_op;
    
    wire [31:0] alu_a, alu_b;
    wire [31:0] alu_result;
    wire alu_zero;
    wire branch_taken;
    wire [31:0] next_pc;
    
    assign pc_plus_4 = pc + 32'h4;
    assign pc_o = pc;
    
    always @(posedge clk or negedge rst_n) begin
        if (!rst_n)
            pc <= 32'h0;
        else
            pc <= next_pc;
    end
    
    assign opcode = instr_i[6:0];
    assign funct3 = instr_i[14:12];
    assign funct7 = instr_i[31:25];
    assign rs1 = instr_i[19:15];
    assign rs2 = instr_i[24:20];
    assign rd = instr_i[11:7];
    
    assign imm = (opcode == 7'b0000011 || opcode == 7'b0010011 || opcode == 7'b1100111) ? {{20{instr_i[31]}}, instr_i[31:20]} :
                 (opcode == 7'b0100011) ? {{20{instr_i[31]}}, instr_i[31:25], instr_i[11:7]} :
                 (opcode == 7'b1100011) ? {{20{instr_i[31]}}, instr_i[7], instr_i[30:25], instr_i[11:8], 1'b0} :
                 (opcode == 7'b0110111 || opcode == 7'b0010111) ? {instr_i[31:12], 12'h0} :
                 (opcode == 7'b1101111) ? {{12{instr_i[31]}}, instr_i[19:12], instr_i[20], instr_i[30:21], 1'b0} :
                 32'h0;
    
    assign imm_type = (opcode == 7'b0000011 || opcode == 7'b0010011) ? 3'b000 :
                      (opcode == 7'b0100011) ? 3'b001 :
                      (opcode == 7'b1100011) ? 3'b010 :
                      (opcode == 7'b0110111 || opcode == 7'b0010111) ? 3'b011 :
                      (opcode == 7'b1101111) ? 3'b100 :
                      3'b000;
    
    control_unit ctrl (
        .opcode     (opcode),
        .funct3     (funct3),
        .funct7     (funct7),
        .reg_write  (reg_write),
        .mem_read   (mem_read),
        .mem_write  (mem_write),
        .alu_op     (alu_op),
        .alu_src_a  (alu_src_a),
        .alu_src_b  (alu_src_b),
        .imm_type   (imm_type),
        .branch     (branch),
        .jump       (jump),
        .jump_reg   (jump_reg),
        .branch_op  (branch_op)
    );
    
    assign rs1_data = (rs1 == 5'h0) ? 32'h0 : reg_file[rs1];
    assign rs2_data = (rs2 == 5'h0) ? 32'h0 : reg_file[rs2];
    
    assign alu_a = (alu_src_a == 2'b01) ? pc :
                   (alu_src_a == 2'b10) ? imm :
                   rs1_data;
    assign alu_b = (alu_src_b == 2'b01) ? imm : rs2_data;
    
    alu alu_inst (
        .a      (alu_a),
        .b      (alu_b),
        .op     (alu_op),
        .result (alu_result),
        .zero   (alu_zero),
        .carry_out(),
        .overflow()
    );
    
    assign branch_taken = branch && (
        (branch_op == 3'b000 && alu_zero) ||
        (branch_op == 3'b001 && ~alu_zero)
    );
    
    assign next_pc = branch_taken ? (pc + imm) : pc_plus_4;
    
    assign addr_o = alu_result;
    assign data_o = rs2_data;
    assign mem_write_o = mem_write;
    assign mem_read_o = mem_read;
    assign halt_o = 1'b0;
    
    integer i;
    always @(posedge clk or negedge rst_n) begin
        if (!rst_n) begin
            for (i = 0; i < 32; i = i + 1)
                reg_file[i] <= 32'h0;
        end else begin
            if (reg_write && rd != 5'h0) begin
                reg_file[rd] <= alu_result;
            end
        end
    end

endmodule

tb/testbench.v
`timescale 1ns/1ps

module testbench;

    reg clk;
    reg rst_n;
    
    wire [31:0] pc;
    wire [31:0] addr;
    wire [31:0] data_o;
    wire        mem_write;
    wire        mem_read;
    wire        halt;
    
    reg [31:0] instr_mem [0:1023];
    reg [31:0] data_mem [0:1023];
    wire [31:0] instr_data;
    wire [31:0] mem_data;
    
    integer test_passed;
    integer test_failed;
    integer cycle_count;
    
    riscv_core dut (
        .clk        (clk),
        .rst_n      (rst_n),
        .instr_i    (instr_data),
        .data_i     (mem_data),
        .pc_o       (pc),
        .addr_o     (addr),
        .data_o     (data_o),
        .mem_write_o(mem_write),
        .mem_read_o (mem_read),
        .halt_o     (halt)
    );
    
    // FIXED: Use PC for instruction memory, not addr
    assign instr_data = instr_mem[pc[11:2]];
    assign mem_data = data_mem[addr[11:2]];
    
    initial begin
        clk = 0;
        forever #5 clk = ~clk;
    end
    
    initial begin
        for (integer i = 0; i < 1024; i = i + 1) begin
            instr_mem[i] = 32'h0;
            data_mem[i] = 32'h0;
        end
        
        $readmemh("tb/tests/rv32ui-p-add.hex", instr_mem);
        
        test_passed = 0;
        test_failed = 0;
        cycle_count = 0;
        
        $display("Instructions loaded:");
        $display("  [0] 0x%08h", instr_mem[0]);
        $display("  [1] 0x%08h", instr_mem[1]);
        $display("  [2] 0x%08h", instr_mem[2]);
        
        rst_n = 0;
        #100;
        rst_n = 1;
        $display("Reset released at time %0t", $time);
        
        while (cycle_count < 100) begin
            @(negedge clk);
            cycle_count = cycle_count + 1;
            
            if (mem_write) begin
                $display("CYCLE %0d: WRITE at addr=0x%08h data=0x%08h pc=0x%08h", 
                         cycle_count, addr, data_o, pc);
                data_mem[addr[11:2]] = data_o;
            end
            
            if (cycle_count < 20) begin
                $display("CYCLE %0d: pc=0x%08h instr=0x%08h mem_write=%0d", 
                         cycle_count, pc, instr_data, mem_write);
            end
        end
        
        #10;
        $display("========================================");
        $display("Final data_mem[0] = 0x%08h", data_mem[0]);
        $display("Expected = 0x0000000A");
        
        if (data_mem[0] == 32'h0000000A) begin
            $display("✅ TEST PASSED!");
            test_passed = 1;
        end else begin
            $display("❌ TEST FAILED!");
            test_failed = 1;
        end
        
        $display("========================================");
        $finish;
    end
    
    initial begin
        $dumpfile("sim/waveforms.vcd");
        $dumpvars(0, testbench);
    end
    
endmodule

sim/waveforms.vcd
$date
	Sun Jul 19 11:49:42 2026
$end
$version
	Icarus Verilog
$end
$timescale
	1ps
$end
$scope module testbench $end
$var wire 1 ! halt $end
$var wire 32 " instr_data [31:0] $end
$var wire 32 # mem_data [31:0] $end
$var wire 32 $ pc [31:0] $end
$var wire 1 % mem_write $end
$var wire 1 & mem_read $end
$var wire 32 ' data_o [31:0] $end
$var wire 32 ( addr [31:0] $end
$var reg 1 ) clk $end
$var reg 1 * rst_n $end
$var integer 32 + cycle_count [31:0] $end
$var integer 32 , test_failed [31:0] $end
$var integer 32 - test_passed [31:0] $end
$scope module dut $end
$var wire 32 . addr_o [31:0] $end
$var wire 1 / branch_taken $end
$var wire 1 ) clk $end
$var wire 32 0 data_i [31:0] $end
$var wire 32 1 data_o [31:0] $end
$var wire 1 ! halt_o $end
$var wire 3 2 imm_type [2:0] $end
$var wire 32 3 instr_i [31:0] $end
$var wire 1 & mem_read_o $end
$var wire 1 % mem_write_o $end
$var wire 32 4 pc_o [31:0] $end
$var wire 1 * rst_n $end
$var wire 32 5 rs2_data [31:0] $end
$var wire 5 6 rs2 [4:0] $end
$var wire 32 7 rs1_data [31:0] $end
$var wire 5 8 rs1 [4:0] $end
$var wire 1 9 reg_write $end
$var wire 5 : rd [4:0] $end
$var wire 32 ; pc_plus_4 [31:0] $end
$var wire 7 < opcode [6:0] $end
$var wire 32 = next_pc [31:0] $end
$var wire 1 > mem_write $end
$var wire 1 ? mem_read $end
$var wire 1 @ jump_reg $end
$var wire 1 A jump $end
$var wire 32 B imm [31:0] $end
$var wire 7 C funct7 [6:0] $end
$var wire 3 D funct3 [2:0] $end
$var wire 3 E branch_op [2:0] $end
$var wire 1 F branch $end
$var wire 1 G alu_zero $end
$var wire 2 H alu_src_b [1:0] $end
$var wire 2 I alu_src_a [1:0] $end
$var wire 32 J alu_result [31:0] $end
$var wire 5 K alu_op [4:0] $end
$var wire 32 L alu_b [31:0] $end
$var wire 32 M alu_a [31:0] $end
$var reg 32 N pc [31:0] $end
$var integer 32 O i [31:0] $end
$scope module alu_inst $end
$var wire 32 P a [31:0] $end
$var wire 32 Q b [31:0] $end
$var wire 1 R overflow $end
$var wire 1 G zero $end
$var wire 5 S op [4:0] $end
$var wire 1 T carry_out $end
$var reg 32 U b_shift [31:0] $end
$var reg 33 V extended_result [32:0] $end
$var reg 64 W mult_result [63:0] $end
$var reg 32 X quotient [31:0] $end
$var reg 32 Y remainder [31:0] $end
$var reg 32 Z result [31:0] $end
$upscope $end
$scope module ctrl $end
$var wire 3 [ funct3 [2:0] $end
$var wire 7 \ funct7 [6:0] $end
$var wire 7 ] opcode [6:0] $end
$var reg 5 ^ alu_op [4:0] $end
$var reg 2 _ alu_src_a [1:0] $end
$var reg 2 ` alu_src_b [1:0] $end
$var reg 1 F branch $end
$var reg 3 a branch_op [2:0] $end
$var reg 3 b imm_type [2:0] $end
$var reg 1 A jump $end
$var reg 1 @ jump_reg $end
$var reg 1 ? mem_read $end
$var reg 1 > mem_write $end
$var reg 1 9 reg_write $end
$upscope $end
$upscope $end
$scope begin $ivl_for_loop1 $end
$var integer 32 c i [31:0] $end
$upscope $end
$upscope $end
$enddefinitions $end
#0
$dumpvars
b10000000000 c
b0 b
b0 a
b1 `
b0 _
b0 ^
b10011 ]
b0 \
b0 [
b1010 Z
b0 Y
b0 X
b0 W
b1010 V
bx U
0T
b0 S
0R
b1010 Q
b0 P
b100000 O
b0 N
b0 M
b1010 L
b0 K
b1010 J
b0 I
b1 H
0G
0F
b0 E
b0 D
b0 C
b1010 B
0A
0@
0?
0>
b100 =
b10011 <
b100 ;
b1010 :
19
b0 8
b0 7
b1010 6
b0 5
b0 4
b101000000000010100010011 3
b0 2
b0 1
b0 0
0/
b1010 .
b0 -
b0 ,
b0 +
0*
0)
b1010 (
b0 '
0&
0%
b0 $
b0 #
b101000000000010100010011 "
0!
$end
#5000
b100000 O
1)
#10000
0)
#15000
b100000 O
1)
#20000
0)
#25000
b100000 O
1)
#30000
0)
#35000
b100000 O
1)
#40000
0)
#45000
b100000 O
1)
#50000
0)
#55000
b100000 O
1)
#60000
0)
#65000
b100000 O
1)
#70000
0)
#75000
b100000 O
1)
#80000
0)
#85000
b100000 O
1)
#90000
0)
#95000
b100000 O
1)
#100000
b1 +
0)
1*
#105000
b0 V
1G
b0 (
b0 .
b0 J
b0 Z
b0 L
b0 Q
b0 B
b1 2
b1 b
1%
1>
b1 H
b1 `
09
b100011 <
b100011 ]
b10 D
b10 [
b0 :
b1010 '
b1010 1
b1010 5
b1000 =
b101000000010000000100011 "
b101000000010000000100011 3
b1000 ;
b100 $
b100 4
b100 N
1)
#110000
b1010 #
b1010 0
b10 +
0)
#115000
19
b0 2
b0 b
b1 H
b1 `
0%
0>
b0 '
b0 1
b0 5
b10011 <
b10011 ]
b0 D
b0 [
b0 6
b1100 =
b10011 "
b10011 3
b1100 ;
b1000 $
b1000 4
b1000 N
1)
#120000
b11 +
0)
#125000
b0 H
b0 `
09
b0 <
b0 ]
b10000 =
b0 "
b0 3
b10000 ;
b1100 $
b1100 4
b1100 N
1)
#130000
b100 +
0)
#135000
b10100 =
b10100 ;
b10000 $
b10000 4
b10000 N
1)
#140000
b101 +
0)
#145000
b11000 =
b11000 ;
b10100 $
b10100 4
b10100 N
1)
#150000
b110 +
0)
#155000
b11100 =
b11100 ;
b11000 $
b11000 4
b11000 N
1)
#160000
b111 +
0)
#165000
b100000 =
b100000 ;
b11100 $
b11100 4
b11100 N
1)
#170000
b1000 +
0)
#175000
b100100 =
b100100 ;
b100000 $
b100000 4
b100000 N
1)
#180000
b1001 +
0)
#185000
b101000 =
b101000 ;
b100100 $
b100100 4
b100100 N
1)
#190000
b1010 +
0)
#195000
b101100 =
b101100 ;
b101000 $
b101000 4
b101000 N
1)
#200000
b1011 +
0)
#205000
b110000 =
b110000 ;
b101100 $
b101100 4
b101100 N
1)
#210000
b1100 +
0)
#215000
b110100 =
b110100 ;
b110000 $
b110000 4
b110000 N
1)
#220000
b1101 +
0)
#225000
b111000 =
b111000 ;
b110100 $
b110100 4
b110100 N
1)
#230000
b1110 +
0)
#235000
b111100 =
b111100 ;
b111000 $
b111000 4
b111000 N
1)
#240000
b1111 +
0)
#245000
b1000000 =
b1000000 ;
b111100 $
b111100 4
b111100 N
1)
#250000
b10000 +
0)
#255000
b1000100 =
b1000100 ;
b1000000 $
b1000000 4
b1000000 N
1)
#260000
b10001 +
0)
#265000
b1001000 =
b1001000 ;
b1000100 $
b1000100 4
b1000100 N
1)
#270000
b10010 +
0)
#275000
b1001100 =
b1001100 ;
b1001000 $
b1001000 4
b1001000 N
1)
#280000
b10011 +
0)
#285000
b1010000 =
b1010000 ;
b1001100 $
b1001100 4
b1001100 N
1)
#290000
b10100 +
0)
#295000
b1010100 =
b1010100 ;
b1010000 $
b1010000 4
b1010000 N
1)
#300000
b10101 +
0)
#305000
b1011000 =
b1011000 ;
b1010100 $
b1010100 4
b1010100 N
1)
#310000
b10110 +
0)
#315000
b1011100 =
b1011100 ;
b1011000 $
b1011000 4
b1011000 N
1)
#320000
b10111 +
0)
#325000
b1100000 =
b1100000 ;
b1011100 $
b1011100 4
b1011100 N
1)
#330000
b11000 +
0)
#335000
b1100100 =
b1100100 ;
b1100000 $
b1100000 4
b1100000 N
1)
#340000
b11001 +
0)
#345000
b1101000 =
b1101000 ;
b1100100 $
b1100100 4
b1100100 N
1)
#350000
b11010 +
0)
#355000
b1101100 =
b1101100 ;
b1101000 $
b1101000 4
b1101000 N
1)
#360000
b11011 +
0)
#365000
b1110000 =
b1110000 ;
b1101100 $
b1101100 4
b1101100 N
1)
#370000
b11100 +
0)
#375000
b1110100 =
b1110100 ;
b1110000 $
b1110000 4
b1110000 N
1)
#380000
b11101 +
0)
#385000
b1111000 =
b1111000 ;
b1110100 $
b1110100 4
b1110100 N
1)
#390000
b11110 +
0)
#395000
b1111100 =
b1111100 ;
b1111000 $
b1111000 4
b1111000 N
1)
#400000
b11111 +
0)
#405000
b10000000 =
b10000000 ;
b1111100 $
b1111100 4
b1111100 N
1)
#410000
b100000 +
0)
#415000
b10000100 =
b10000100 ;
b10000000 $
b10000000 4
b10000000 N
1)
#420000
b100001 +
0)
#425000
b10001000 =
b10001000 ;
b10000100 $
b10000100 4
b10000100 N
1)
#430000
b100010 +
0)
#435000
b10001100 =
b10001100 ;
b10001000 $
b10001000 4
b10001000 N
1)
#440000
b100011 +
0)
#445000
b10010000 =
b10010000 ;
b10001100 $
b10001100 4
b10001100 N
1)
#450000
b100100 +
0)
#455000
b10010100 =
b10010100 ;
b10010000 $
b10010000 4
b10010000 N
1)
#460000
b100101 +
0)
#465000
b10011000 =
b10011000 ;
b10010100 $
b10010100 4
b10010100 N
1)
#470000
b100110 +
0)
#475000
b10011100 =
b10011100 ;
b10011000 $
b10011000 4
b10011000 N
1)
#480000
b100111 +
0)
#485000
b10100000 =
b10100000 ;
b10011100 $
b10011100 4
b10011100 N
1)
#490000
b101000 +
0)
#495000
b10100100 =
b10100100 ;
b10100000 $
b10100000 4
b10100000 N
1)
#500000
b101001 +
0)
#505000
b10101000 =
b10101000 ;
b10100100 $
b10100100 4
b10100100 N
1)
#510000
b101010 +
0)
#515000
b10101100 =
b10101100 ;
b10101000 $
b10101000 4
b10101000 N
1)
#520000
b101011 +
0)
#525000
b10110000 =
b10110000 ;
b10101100 $
b10101100 4
b10101100 N
1)
#530000
b101100 +
0)
#535000
b10110100 =
b10110100 ;
b10110000 $
b10110000 4
b10110000 N
1)
#540000
b101101 +
0)
#545000
b10111000 =
b10111000 ;
b10110100 $
b10110100 4
b10110100 N
1)
#550000
b101110 +
0)
#555000
b10111100 =
b10111100 ;
b10111000 $
b10111000 4
b10111000 N
1)
#560000
b101111 +
0)
#565000
b11000000 =
b11000000 ;
b10111100 $
b10111100 4
b10111100 N
1)
#570000
b110000 +
0)
#575000
b11000100 =
b11000100 ;
b11000000 $
b11000000 4
b11000000 N
1)
#580000
b110001 +
0)
#585000
b11001000 =
b11001000 ;
b11000100 $
b11000100 4
b11000100 N
1)
#590000
b110010 +
0)
#595000
b11001100 =
b11001100 ;
b11001000 $
b11001000 4
b11001000 N
1)
#600000
b110011 +
0)
#605000
b11010000 =
b11010000 ;
b11001100 $
b11001100 4
b11001100 N
1)
#610000
b110100 +
0)
#615000
b11010100 =
b11010100 ;
b11010000 $
b11010000 4
b11010000 N
1)
#620000
b110101 +
0)
#625000
b11011000 =
b11011000 ;
b11010100 $
b11010100 4
b11010100 N
1)
#630000
b110110 +
0)
#635000
b11011100 =
b11011100 ;
b11011000 $
b11011000 4
b11011000 N
1)
#640000
b110111 +
0)
#645000
b11100000 =
b11100000 ;
b11011100 $
b11011100 4
b11011100 N
1)
#650000
b111000 +
0)
#655000
b11100100 =
b11100100 ;
b11100000 $
b11100000 4
b11100000 N
1)
#660000
b111001 +
0)
#665000
b11101000 =
b11101000 ;
b11100100 $
b11100100 4
b11100100 N
1)
#670000
b111010 +
0)
#675000
b11101100 =
b11101100 ;
b11101000 $
b11101000 4
b11101000 N
1)
#680000
b111011 +
0)
#685000
b11110000 =
b11110000 ;
b11101100 $
b11101100 4
b11101100 N
1)
#690000
b111100 +
0)
#695000
b11110100 =
b11110100 ;
b11110000 $
b11110000 4
b11110000 N
1)
#700000
b111101 +
0)
#705000
b11111000 =
b11111000 ;
b11110100 $
b11110100 4
b11110100 N
1)
#710000
b111110 +
0)
#715000
b11111100 =
b11111100 ;
b11111000 $
b11111000 4
b11111000 N
1)
#720000
b111111 +
0)
#725000
b100000000 =
b100000000 ;
b11111100 $
b11111100 4
b11111100 N
1)
#730000
b1000000 +
0)
#735000
b100000100 =
b100000100 ;
b100000000 $
b100000000 4
b100000000 N
1)
#740000
b1000001 +
0)
#745000
b100001000 =
b100001000 ;
b100000100 $
b100000100 4
b100000100 N
1)
#750000
b1000010 +
0)
#755000
b100001100 =
b100001100 ;
b100001000 $
b100001000 4
b100001000 N
1)
#760000
b1000011 +
0)
#765000
b100010000 =
b100010000 ;
b100001100 $
b100001100 4
b100001100 N
1)
#770000
b1000100 +
0)
#775000
b100010100 =
b100010100 ;
b100010000 $
b100010000 4
b100010000 N
1)
#780000
b1000101 +
0)
#785000
b100011000 =
b100011000 ;
b100010100 $
b100010100 4
b100010100 N
1)
#790000
b1000110 +
0)
#795000
b100011100 =
b100011100 ;
b100011000 $
b100011000 4
b100011000 N
1)
#800000
b1000111 +
0)
#805000
b100100000 =
b100100000 ;
b100011100 $
b100011100 4
b100011100 N
1)
#810000
b1001000 +
0)
#815000
b100100100 =
b100100100 ;
b100100000 $
b100100000 4
b100100000 N
1)
#820000
b1001001 +
0)
#825000
b100101000 =
b100101000 ;
b100100100 $
b100100100 4
b100100100 N
1)
#830000
b1001010 +
0)
#835000
b100101100 =
b100101100 ;
b100101000 $
b100101000 4
b100101000 N
1)
#840000
b1001011 +
0)
#845000
b100110000 =
b100110000 ;
b100101100 $
b100101100 4
b100101100 N
1)
#850000
b1001100 +
0)
#855000
b100110100 =
b100110100 ;
b100110000 $
b100110000 4
b100110000 N
1)
#860000
b1001101 +
0)
#865000
b100111000 =
b100111000 ;
b100110100 $
b100110100 4
b100110100 N
1)
#870000
b1001110 +
0)
#875000
b100111100 =
b100111100 ;
b100111000 $
b100111000 4
b100111000 N
1)
#880000
b1001111 +
0)
#885000
b101000000 =
b101000000 ;
b100111100 $
b100111100 4
b100111100 N
1)
#890000
b1010000 +
0)
#895000
b101000100 =
b101000100 ;
b101000000 $
b101000000 4
b101000000 N
1)
#900000
b1010001 +
0)
#905000
b101001000 =
b101001000 ;
b101000100 $
b101000100 4
b101000100 N
1)
#910000
b1010010 +
0)
#915000
b101001100 =
b101001100 ;
b101001000 $
b101001000 4
b101001000 N
1)
#920000
b1010011 +
0)
#925000
b101010000 =
b101010000 ;
b101001100 $
b101001100 4
b101001100 N
1)
#930000
b1010100 +
0)
#935000
b101010100 =
b101010100 ;
b101010000 $
b101010000 4
b101010000 N
1)
#940000
b1010101 +
0)
#945000
b101011000 =
b101011000 ;
b101010100 $
b101010100 4
b101010100 N
1)
#950000
b1010110 +
0)
#955000
b101011100 =
b101011100 ;
b101011000 $
b101011000 4
b101011000 N
1)
#960000
b1010111 +
0)
#965000
b101100000 =
b101100000 ;
b101011100 $
b101011100 4
b101011100 N
1)
#970000
b1011000 +
0)
#975000
b101100100 =
b101100100 ;
b101100000 $
b101100000 4
b101100000 N
1)
#980000
b1011001 +
0)
#985000
b101101000 =
b101101000 ;
b101100100 $
b101100100 4
b101100100 N
1)
#990000
b1011010 +
0)
