rtl/core/riscv_core.v
module riscv_core (
    input  wire        clk,
    input  wire        rst_n,
    input  wire [31:0] instr_i,
    input  wire [31:0] data_i,
    output wire [31:0] pc_o,
    output wire [31:0] addr_o,
    output wire [31:0] data_o,
    output wire        mem_write_o,
    output wire        mem_read_o,
    output wire        halt_o
);

    // ============ PC ============
    reg [31:0] pc;
    
    always @(posedge clk or negedge rst_n) begin
        if (!rst_n) begin
            pc <= 32'h0;
        end else begin
            pc <= pc + 32'h4;
        end
    end
    
    assign pc_o = pc;
    
    // ============ DECODE ============
    wire [6:0] opcode = instr_i[6:0];
    wire [2:0] funct3 = instr_i[14:12];
    wire [6:0] funct7 = instr_i[31:25];
    wire [4:0] rs1 = instr_i[19:15];
    wire [4:0] rs2 = instr_i[24:20];
    wire [4:0] rd = instr_i[11:7];
    
    // ============ IMMEDIATE ============
    wire [31:0] imm_i = {{20{instr_i[31]}}, instr_i[31:20]};
    wire [31:0] imm_s = {{20{instr_i[31]}}, instr_i[31:25], instr_i[11:7]};
    wire [31:0] imm_b = {{20{instr_i[31]}}, instr_i[7], instr_i[30:25], instr_i[11:8], 1'b0};
    wire [31:0] imm_u = {instr_i[31:12], 12'h0};
    wire [31:0] imm_j = {{12{instr_i[31]}}, instr_i[19:12], instr_i[20], instr_i[30:21], 1'b0};
    
    reg [31:0] imm;
    
    always @(*) begin
        case (opcode)
            7'b0000011: imm = imm_i; // LOAD
            7'b0100011: imm = imm_s; // STORE
            7'b0010011: imm = imm_i; // OP-IMM
            7'b0110011: imm = 32'h0; // OP
            7'b1100011: imm = imm_b; // BRANCH
            7'b1101111: imm = imm_j; // JAL
            7'b0110111: imm = imm_u; // LUI
            default: imm = 32'h0;
        endcase
    end
    
    // ============ CONTROL ============
    reg reg_write, mem_read, mem_write;
    reg [3:0] alu_op;
    reg [1:0] alu_src_a, alu_src_b;
    
    always @(*) begin
        reg_write = 1'b0;
        mem_read = 1'b0;
        mem_write = 1'b0;
        alu_op = 4'h0;
        alu_src_a = 2'b00;
        alu_src_b = 2'b00;
        
        case (opcode)
            7'b0000011: begin // LOAD
                reg_write = 1'b1;
                mem_read = 1'b1;
                alu_src_a = 2'b00;
                alu_src_b = 2'b01;
                alu_op = 4'h0;
            end
            
            7'b0100011: begin // STORE
                mem_write = 1'b1;
                alu_src_a = 2'b00;
                alu_src_b = 2'b01;
                alu_op = 4'h0;
            end
            
            7'b0010011: begin // OP-IMM
                reg_write = 1'b1;
                alu_src_a = 2'b00;
                alu_src_b = 2'b01;
                alu_op = 4'h0;
            end
            
            7'b0110011: begin // OP
                reg_write = 1'b1;
                alu_src_a = 2'b00;
                alu_src_b = 2'b00;
                alu_op = 4'h0;
            end
        endcase
    end
    
    // ============ REGISTER FILE ============
    reg [31:0] reg_file [0:31];
    wire [31:0] rs1_data, rs2_data;
    
    assign rs1_data = (rs1 == 5'h0) ? 32'h0 : reg_file[rs1];
    assign rs2_data = (rs2 == 5'h0) ? 32'h0 : reg_file[rs2];
    
    always @(posedge clk or negedge rst_n) begin
        if (!rst_n) begin
            for (integer i = 0; i < 32; i = i + 1)
                reg_file[i] <= 32'h0;
        end else begin
            if (reg_write && rd != 5'h0) begin
                reg_file[rd] <= alu_result;
            end
        end
    end
    
    // ============ ALU ============
    wire [31:0] alu_a, alu_b;
    reg [31:0] alu_result;
    
    assign alu_a = (alu_src_a == 2'b01) ? pc :
                   (alu_src_a == 2'b10) ? imm :
                   rs1_data;
                   
    assign alu_b = (alu_src_b == 2'b01) ? imm : rs2_data;
    
    always @(*) begin
        case (alu_op)
            4'h0: alu_result = alu_a + alu_b;
            4'h1: alu_result = alu_a - alu_b;
            4'h2: alu_result = alu_a & alu_b;
            4'h3: alu_result = alu_a | alu_b;
            4'h4: alu_result = alu_a ^ alu_b;
            default: alu_result = alu_a + alu_b;
        endcase
    end
    
    // ============ MEMORY ============
    assign addr_o = alu_result;
    assign data_o = rs2_data;
    assign mem_write_o = mem_write;
    assign mem_read_o = mem_read;
    assign halt_o = 1'b0;

endmodule

tb/testbench.v
`timescale 1ns/1ps

module testbench;

    reg clk;
    reg rst_n;
    
    wire [31:0] pc;
    wire [31:0] addr;
    wire [31:0] data_o;
    wire        mem_write;
    wire        mem_read;
    wire        halt;
    
    reg [31:0] instr_mem [0:1023];
    reg [31:0] data_mem [0:1023];
    wire [31:0] instr_data;
    wire [31:0] mem_data;
    
    integer test_passed;
    integer test_failed;
    integer cycle_count;
    
    riscv_core dut (
        .clk        (clk),
        .rst_n      (rst_n),
        .instr_i    (instr_data),
        .data_i     (mem_data),
        .pc_o       (pc),
        .addr_o     (addr),
        .data_o     (data_o),
        .mem_write_o(mem_write),
        .mem_read_o (mem_read),
        .halt_o     (halt)
    );
    
    // FIXED: Use PC for instruction memory, not addr
    assign instr_data = instr_mem[pc[11:2]];
    assign mem_data = data_mem[addr[11:2]];
    
    initial begin
        clk = 0;
        forever #5 clk = ~clk;
    end
    
    initial begin
        for (integer i = 0; i < 1024; i = i + 1) begin
            instr_mem[i] = 32'h0;
            data_mem[i] = 32'h0;
        end
        
        $readmemh("tb/tests/rv32ui-p-add.hex", instr_mem);
        
        test_passed = 0;
        test_failed = 0;
        cycle_count = 0;
        
        $display("Instructions loaded:");
        $display("  [0] 0x%08h", instr_mem[0]);
        $display("  [1] 0x%08h", instr_mem[1]);
        $display("  [2] 0x%08h", instr_mem[2]);
        
        rst_n = 0;
        #100;
        rst_n = 1;
        $display("Reset released at time %0t", $time);
        
        while (cycle_count < 100) begin
            @(negedge clk);
            cycle_count = cycle_count + 1;
            
            if (mem_write) begin
                $display("CYCLE %0d: WRITE at addr=0x%08h data=0x%08h pc=0x%08h", 
                         cycle_count, addr, data_o, pc);
                data_mem[addr[11:2]] = data_o;
            end
            
            if (cycle_count < 20) begin
                $display("CYCLE %0d: pc=0x%08h instr=0x%08h mem_write=%0d", 
                         cycle_count, pc, instr_data, mem_write);
            end
        end
        
        #10;
        $display("========================================");
        $display("Final data_mem[0] = 0x%08h", data_mem[0]);
        $display("Expected = 0x0000000A");
        
        if (data_mem[0] == 32'h0000000A) begin
            $display("✅ TEST PASSED!");
            test_passed = 1;
        end else begin
            $display("❌ TEST FAILED!");
            test_failed = 1;
        end
        
        $display("========================================");
        $finish;
    end
    
    initial begin
        $dumpfile("sim/waveforms.vcd");
        $dumpvars(0, testbench);
    end
    
endmodule

sim/waveforms.vcd
$date
	Sun Jul 19 08:58:29 2026
$end
$version
	Icarus Verilog
$end
$timescale
	1ps
$end
$scope module testbench $end
$var wire 1 ! halt $end
$var wire 32 " instr_data [31:0] $end
$var wire 32 # mem_data [31:0] $end
$var wire 32 $ pc [31:0] $end
$var wire 1 % mem_write $end
$var wire 1 & mem_read $end
$var wire 32 ' data_o [31:0] $end
$var wire 32 ( addr [31:0] $end
$var reg 1 ) clk $end
$var reg 1 * rst_n $end
$var integer 32 + cycle_count [31:0] $end
$var integer 32 , test_failed [31:0] $end
$var integer 32 - test_passed [31:0] $end
$scope module dut $end
$var wire 1 ) clk $end
$var wire 32 . data_i [31:0] $end
$var wire 32 / data_o [31:0] $end
$var wire 1 ! halt_o $end
$var wire 32 0 instr_i [31:0] $end
$var wire 1 & mem_read_o $end
$var wire 1 % mem_write_o $end
$var wire 32 1 pc_o [31:0] $end
$var wire 1 * rst_n $end
$var wire 32 2 rs2_data [31:0] $end
$var wire 5 3 rs2 [4:0] $end
$var wire 32 4 rs1_data [31:0] $end
$var wire 5 5 rs1 [4:0] $end
$var wire 5 6 rd [4:0] $end
$var wire 7 7 opcode [6:0] $end
$var wire 32 8 imm_u [31:0] $end
$var wire 32 9 imm_s [31:0] $end
$var wire 32 : imm_j [31:0] $end
$var wire 32 ; imm_i [31:0] $end
$var wire 32 < imm_b [31:0] $end
$var wire 7 = funct7 [6:0] $end
$var wire 3 > funct3 [2:0] $end
$var wire 32 ? alu_b [31:0] $end
$var wire 32 @ alu_a [31:0] $end
$var wire 32 A addr_o [31:0] $end
$var reg 4 B alu_op [3:0] $end
$var reg 32 C alu_result [31:0] $end
$var reg 2 D alu_src_a [1:0] $end
$var reg 2 E alu_src_b [1:0] $end
$var reg 32 F imm [31:0] $end
$var reg 1 G mem_read $end
$var reg 1 H mem_write $end
$var reg 32 I pc [31:0] $end
$var reg 1 J reg_write $end
$scope begin $ivl_for_loop0 $end
$var integer 32 K i [31:0] $end
$upscope $end
$upscope $end
$scope begin $ivl_for_loop2 $end
$var integer 32 L i [31:0] $end
$upscope $end
$upscope $end
$enddefinitions $end
#0
$dumpvars
b10000000000 L
b100000 K
1J
b0 I
0H
0G
b1010 F
b1 E
b0 D
b1010 C
b0 B
b1010 A
b0 @
b1010 ?
b0 >
b0 =
b1010 <
b1010 ;
b1010 :
b1010 9
b101000000000000000000000 8
b10011 7
b1010 6
b0 5
b0 4
b1010 3
b0 2
b0 1
b101000000000010100010011 0
b0 /
b0 .
b0 -
b0 ,
b0 +
0*
0)
b1010 (
b0 '
0&
0%
b0 $
b0 #
b101000000000010100010011 "
0!
$end
#5000
b100000 K
1)
#10000
0)
#15000
b100000 K
1)
#20000
0)
#25000
b100000 K
1)
#30000
0)
#35000
b100000 K
1)
#40000
0)
#45000
b100000 K
1)
#50000
0)
#55000
b100000 K
1)
#60000
0)
#65000
b100000 K
1)
#70000
0)
#75000
b100000 K
1)
#80000
0)
#85000
b100000 K
1)
#90000
0)
#95000
b100000 K
1)
#100000
b1 +
0)
1*
#105000
b0 (
b0 A
b0 C
b0 ?
1%
1H
b1 E
0J
b0 F
b100011 7
b10 >
b0 6
b0 9
b0 <
b101000000010000000000000 8
b10000000001010 :
b101000000010000000100011 "
b101000000010000000100011 0
b1010 '
b1010 /
b1010 2
b100 $
b100 1
b100 I
1)
#110000
b1010 #
b1010 .
b10 +
0)
#115000
1J
b1 E
0%
0H
b0 '
b0 /
b0 2
b10011 7
b0 >
b0 3
b0 ;
b0 8
b0 :
b10011 "
b10011 0
b1000 $
b1000 1
b1000 I
1)
#120000
b11 +
0)
#125000
b0 E
0J
b0 7
b0 "
b0 0
b1100 $
b1100 1
b1100 I
1)
#130000
b100 +
0)
#135000
b10000 $
b10000 1
b10000 I
1)
#140000
b101 +
0)
#145000
b10100 $
b10100 1
b10100 I
1)
#150000
b110 +
0)
#155000
b11000 $
b11000 1
b11000 I
1)
#160000
b111 +
0)
#165000
b11100 $
b11100 1
b11100 I
1)
#170000
b1000 +
0)
#175000
b100000 $
b100000 1
b100000 I
1)
#180000
b1001 +
0)
#185000
b100100 $
b100100 1
b100100 I
1)
#190000
b1010 +
0)
#195000
b101000 $
b101000 1
b101000 I
1)
#200000
b1011 +
0)
#205000
b101100 $
b101100 1
b101100 I
1)
#210000
b1100 +
0)
#215000
b110000 $
b110000 1
b110000 I
1)
#220000
b1101 +
0)
#225000
b110100 $
b110100 1
b110100 I
1)
#230000
b1110 +
0)
#235000
b111000 $
b111000 1
b111000 I
1)
#240000
b1111 +
0)
#245000
b111100 $
b111100 1
b111100 I
1)
#250000
b10000 +
0)
#255000
b1000000 $
b1000000 1
b1000000 I
1)
#260000
b10001 +
0)
#265000
b1000100 $
b1000100 1
b1000100 I
1)
#270000
b10010 +
0)
#275000
b1001000 $
b1001000 1
b1001000 I
1)
#280000
b10011 +
0)
#285000
b1001100 $
b1001100 1
b1001100 I
1)
#290000
b10100 +
0)
#295000
b1010000 $
b1010000 1
b1010000 I
1)
#300000
b10101 +
0)
#305000
b1010100 $
b1010100 1
b1010100 I
1)
#310000
b10110 +
0)
#315000
b1011000 $
b1011000 1
b1011000 I
1)
#320000
b10111 +
0)
#325000
b1011100 $
b1011100 1
b1011100 I
1)
#330000
b11000 +
0)
#335000
b1100000 $
b1100000 1
b1100000 I
1)
#340000
b11001 +
0)
#345000
b1100100 $
b1100100 1
b1100100 I
1)
#350000
b11010 +
0)
#355000
b1101000 $
b1101000 1
b1101000 I
1)
#360000
b11011 +
0)
#365000
b1101100 $
b1101100 1
b1101100 I
1)
#370000
b11100 +
0)
#375000
b1110000 $
b1110000 1
b1110000 I
1)
#380000
b11101 +
0)
#385000
b1110100 $
b1110100 1
b1110100 I
1)
#390000
b11110 +
0)
#395000
b1111000 $
b1111000 1
b1111000 I
1)
#400000
b11111 +
0)
#405000
b1111100 $
b1111100 1
b1111100 I
1)
#410000
b100000 +
0)
#415000
b10000000 $
b10000000 1
b10000000 I
1)
#420000
b100001 +
0)
#425000
b10000100 $
b10000100 1
b10000100 I
1)
#430000
b100010 +
0)
#435000
b10001000 $
b10001000 1
b10001000 I
1)
#440000
b100011 +
0)
#445000
b10001100 $
b10001100 1
b10001100 I
1)
#450000
b100100 +
0)
#455000
b10010000 $
b10010000 1
b10010000 I
1)
#460000
b100101 +
0)
#465000
b10010100 $
b10010100 1
b10010100 I
1)
#470000
b100110 +
0)
#475000
b10011000 $
b10011000 1
b10011000 I
1)
#480000
b100111 +
0)
#485000
b10011100 $
b10011100 1
b10011100 I
1)
#490000
b101000 +
0)
#495000
b10100000 $
b10100000 1
b10100000 I
1)
#500000
b101001 +
0)
#505000
b10100100 $
b10100100 1
b10100100 I
1)
#510000
b101010 +
0)
#515000
b10101000 $
b10101000 1
b10101000 I
1)
#520000
b101011 +
0)
#525000
b10101100 $
b10101100 1
b10101100 I
1)
#530000
b101100 +
0)
#535000
b10110000 $
b10110000 1
b10110000 I
1)
#540000
b101101 +
0)
#545000
b10110100 $
b10110100 1
b10110100 I
1)
#550000
b101110 +
0)
#555000
b10111000 $
b10111000 1
b10111000 I
1)
#560000
b101111 +
0)
#565000
b10111100 $
b10111100 1
b10111100 I
1)
#570000
b110000 +
0)
#575000
b11000000 $
b11000000 1
b11000000 I
1)
#580000
b110001 +
0)
#585000
b11000100 $
b11000100 1
b11000100 I
1)
#590000
b110010 +
0)
#595000
b11001000 $
b11001000 1
b11001000 I
1)
#600000
b110011 +
0)
#605000
b11001100 $
b11001100 1
b11001100 I
1)
#610000
b110100 +
0)
#615000
b11010000 $
b11010000 1
b11010000 I
1)
#620000
b110101 +
0)
#625000
b11010100 $
b11010100 1
b11010100 I
1)
#630000
b110110 +
0)
#635000
b11011000 $
b11011000 1
b11011000 I
1)
#640000
b110111 +
0)
#645000
b11011100 $
b11011100 1
b11011100 I
1)
#650000
b111000 +
0)
#655000
b11100000 $
b11100000 1
b11100000 I
1)
#660000
b111001 +
0)
#665000
b11100100 $
b11100100 1
b11100100 I
1)
#670000
b111010 +
0)
#675000
b11101000 $
b11101000 1
b11101000 I
1)
#680000
b111011 +
0)
#685000
b11101100 $
b11101100 1
b11101100 I
1)
#690000
b111100 +
0)
#695000
b11110000 $
b11110000 1
b11110000 I
1)
#700000
b111101 +
0)
#705000
b11110100 $
b11110100 1
b11110100 I
1)
#710000
b111110 +
0)
#715000
b11111000 $
b11111000 1
b11111000 I
1)
#720000
b111111 +
0)
#725000
b11111100 $
b11111100 1
b11111100 I
1)
#730000
b1000000 +
0)
#735000
b100000000 $
b100000000 1
b100000000 I
1)
#740000
b1000001 +
0)
#745000
b100000100 $
b100000100 1
b100000100 I
1)
#750000
b1000010 +
0)
#755000
b100001000 $
b100001000 1
b100001000 I
1)
#760000
b1000011 +
0)
#765000
b100001100 $
b100001100 1
b100001100 I
1)
#770000
b1000100 +
0)
#775000
b100010000 $
b100010000 1
b100010000 I
1)
#780000
b1000101 +
0)
#785000
b100010100 $
b100010100 1
b100010100 I
1)
#790000
b1000110 +
0)
#795000
b100011000 $
b100011000 1
b100011000 I
1)
#800000
b1000111 +
0)
#805000
b100011100 $
b100011100 1
b100011100 I
1)
#810000
b1001000 +
0)
#815000
b100100000 $
b100100000 1
b100100000 I
1)
#820000
b1001001 +
0)
#825000
b100100100 $
b100100100 1
b100100100 I
1)
#830000
b1001010 +
0)
#835000
b100101000 $
b100101000 1
b100101000 I
1)
#840000
b1001011 +
0)
#845000
b100101100 $
b100101100 1
b100101100 I
1)
#850000
b1001100 +
0)
#855000
b100110000 $
b100110000 1
b100110000 I
1)
#860000
b1001101 +
0)
#865000
b100110100 $
b100110100 1
b100110100 I
1)
#870000
b1001110 +
0)
#875000
b100111000 $
b100111000 1
b100111000 I
1)
#880000
b1001111 +
0)
#885000
b100111100 $
b100111100 1
b100111100 I
1)
#890000
b1010000 +
0)
#895000
b101000000 $
b101000000 1
b101000000 I
1)
#900000
b1010001 +
0)
#905000
b101000100 $
b101000100 1
b101000100 I
1)
#910000
b1010010 +
0)
#915000
b101001000 $
b101001000 1
b101001000 I
1)
#920000
b1010011 +
0)
#925000
b101001100 $
b101001100 1
b101001100 I
1)
#930000
b1010100 +
0)
#935000
b101010000 $
b101010000 1
b101010000 I
1)
#940000
b1010101 +
0)
#945000
b101010100 $
b101010100 1
b101010100 I
1)
#950000
b1010110 +
0)
#955000
b101011000 $
b101011000 1
b101011000 I
1)
#960000
b1010111 +
0)
#965000
b101011100 $
b101011100 1
b101011100 I
1)
#970000
b1011000 +
0)
#975000
b101100000 $
b101100000 1
b101100000 I
1)
#980000
b1011001 +
0)
#985000
b101100100 $
b101100100 1
b101100100 I
1)
#990000
b1011010 +
0)
#995000
b101101000 $
b101101000 1
b101101000 I
1)
#1000000
b1011011 +
0)
#1005000
b101101100 $
b101101100 1
b101101100 I
1)
#1010000
b1011100 +
0)
#1015000
b101110000 $
b101110000 1
b101110000 I
1)
#1020000
b1011101 +
0)
#1025000
b101110100 $
b101110100 1
b101110100 I
1)
#1030000
b1011110 +
0)
#1035000
b101111000 $
b101111000 1
b101111000 I
1)
#1040000
b1011111 +
0)
#1045000
b101111100 $
b101111100 1
b101111100 I
1)
#1050000
b1100000 +
0)
#1055000
b110000000 $
b110000000 1
b110000000 I
1)
#1060000
b1100001 +
0)
#1065000
b110000100 $
b110000100 1
b110000100 I
1)
#1070000
b1100010 +
0)
#1075000
b110001000 $
b110001000 1
b110001000 I
1)
#1080000
b1100011 +
0)
#1085000
b110001100 $
b110001100 1
b110001100 I
1)
#1090000
b1100100 +
0)
#1095000
b110010000 $
b110010000 1
b110010000 I
1)
#1100000
0)
b1 -
